{"nodes": [{"id": "d_repos_selek55_avansas_src_avansas_domain_entities_productimage_cs", "label": "ProductImage.cs", "file_type": "code", "source_file": "D:\\repos\\selek55\\avansas\\src\\Avansas.Domain\\Entities\\ProductImage.cs", "source_location": "L1"}, {"id": "productimage_productimage", "label": "ProductImage", "file_type": "code", "source_file": "D:\\repos\\selek55\\avansas\\src\\Avansas.Domain\\Entities\\ProductImage.cs", "source_location": "L3"}, {"id": "baseentity", "label": "BaseEntity", "file_type": "code", "source_file": "", "source_location": ""}], "edges": [{"source": "d_repos_selek55_avansas_src_avansas_domain_entities_productimage_cs", "target": "productimage_productimage", "relation": "contains", "confidence": "EXTRACTED", "source_file": "D:\\repos\\selek55\\avansas\\src\\Avansas.Domain\\Entities\\ProductImage.cs", "source_location": "L3", "weight": 1.0}, {"source": "productimage_productimage", "target": "baseentity", "relation": "inherits", "confidence": "EXTRACTED", "source_file": "D:\\repos\\selek55\\avansas\\src\\Avansas.Domain\\Entities\\ProductImage.cs", "source_location": "L3", "weight": 1.0}], "raw_calls": []}